Workbook

Sheet Financial Analysis 
A2: Cashflow | B2: Description | C2: Year 0 | D2: Year 1 | E2: Year 2 | F2: Year 3 | G2: Year 4 | H2: Year 5
A3: Initial Investment | B3: Initial Seed funding received from an investor or bootstrapped. | C3: 100000
A4: Expenses
A5: Salaries | B5: Developer, board members salaries. | D5: =$B$42*D10 -> 300000 | E5: =$B$42*E10 -> 360000 | F5: =$B$42*F10 -> 420000 | G5: =$B$42*G10 -> 480000 | H5: =$B$42*H10 -> 540000
A6: Platform APIs | B6: Variable costs for API tokens - like firebase | D6: =$B$29 -> 720 | E6: =$B$29 -> 720 | F6: =$B$29 -> 720 | G6: =$B$29 -> 720 | H6: =$B$29 -> 720
A7: Server | B7: Variable costs for AWS | D7: =$B$30 -> 540 | E7: =$B$30 -> 540 | F7: =$B$30 -> 540 | G7: =$B$30 -> 540 | H7: =$B$30 -> 540
A8: Marketing - CAC | B8: Variable costs for internet marketing on Google Ads/ similar Customer acquisition costs. | D8: =$B$31*$B$32*D9 -> 662.904 | E8: =$B$31*$B$32*E9 -> 742.45248 | F8: =$B$31*$B$32*F9 -> 831.54678 | G8: =$B$31*$B$32*G9 -> 931.33239 | H8: =$B$31*$B$32*H9 -> 1043.0923
A9: Number of users | B9: Number of users of the platform. This number is expected to grow at a rate mentioned below. The number is derived from comparing similar copmanies customer growth. | D9: =$B$36*$B$35 -> 15840 | E9: =D9*1.12 -> 17740.8 | F9: =E9*1.12 -> 19869.696 | G9: =F9*1.12 -> 22254.06 | H9: =G9*1.12 -> 24924.547
A10: Number of employees | B10: Number of employees hired per year. Iniatially building ourselves and then hiring 1 employee per year to manage- software bugs and issues. | D10: 5 | E10: =ROUNDUP(D10*1.12, 0) -> 6 | F10: =ROUNDUP(E10*1.12, 0) -> 7 | G10: =ROUNDUP(F10*1.12, 0) -> 8 | H10: =ROUNDUP(G10*1.12, 0) -> 9
A12: EBITA
A13: TAX
A14: Total Costs | C14: =SUM(C3:C13) -> 100000 | D14: =SUM(D5:D10) -> 317767.9 | E14: =SUM(E5:E10) -> 379749.25 | F14: =SUM(F5:F10) -> 441968.24 | G14: =SUM(G5:G10) -> 504453.39 | H14: =SUM(H5:H10) -> 567236.64
A15: Revenue (Refer to Revenue Model)
A16: Advertising and analytics revenue | C16: 0 | D16: ='Revenue Model '!C3 -> 500000 | E16: ='Revenue Model '!C4 -> 550000 | F16: ='Revenue Model '!C5 -> 605000 | G16: ='Revenue Model '!C6 -> 665500 | H16: ='Revenue Model '!C7 -> 732050
A17: Premium Subscription | C17: $ | D17: 167700 | E17: 184470 | F17: 202917 | G17: 223208.7 | H17: 245529.57
A18: Real estate alliances | C18: $ | D18: 100000 | E18: 110000 | F18: 121000 | G18: 133100 | H18: 146410
A20: Total Revenues | C20: =SUM(C16:C19) -> 0 | D20: =SUM(D16:D19) -> 767700 | E20: =SUM(E16:E19) -> 844470 | F20: =SUM(F16:F19) -> 928917 | G20: =SUM(G16:G19) -> 1021808.7 | H20: =SUM(H16:H19) -> 1123989.6
A21: Net Cashflow | B21: Revenue - Expenses | C21: =C16-C14 -> -100000 | D21: =D20-D14 -> 449932.1 | E21: =E20-E14 -> 464720.75 | F21: =F20-F14 -> 486948.76 | G21: =G20-G14 -> 517355.31 | H21: =H20-H14 -> 556752.93
A23: Discounting Rate | B23: 0.1 | C23: Given in the assignment instructions
A24: NPV | B24: =NPV(B23, C21:H21) -> 1598189.2
A25: Assumptions | B25: Value | C25: Reference
A29: Firebase | B29: =60*12 -> 720 | C29: https://firebase.google.com/pricing
A30: AWS | B30: =45*12 -> 540 | C30: https://calculator.aws/#/addService
A31: Google Ads CPC | B31: 0.279 | C31: https://bard.google.com/?utm_source=sem&utm_medium=paid-media&utm_campaign=q3enUS_sem7
A32: Typical conersion rate for SaaS early stage | B32: 0.15 | C32: https://www.subscriptionflow.com/2022/12/saas-startups-what-is-a-good-demo-conversion-rate/#:~:text=SaaS%20companies%20often%20focus%20on,at%20around%2015%25%2D20%25.
A33: Market Size for student housing (TAM) | B33: 11000000000 | C33: https://www.google.com/url?sa=t&rct=j&q=&esrc=s&source=web&cd=&cad=rja&uact=8&ved=2ahUKEwjpqJSCo7-BAxWWLUQIHRPgCG0QFnoECBYQAw&url=https%3A%2F%2Fwww.linkedin.com%2Fpulse%2Fstudent-housing-market-size-2030-consumer-goods-insights%23%3A~%3Atext%3DThe%2520global%2520Student%2520Housing%2520market%2520size%2520was%2520valued%2520at%2520USD%2CUSD%252014700.0%2520million%2520by%25202027.&usg=AOvVaw1qleiRTvpBOUFWyAVKIE2R&opi=89978449
A34: Market size USC students living in housing around DPS (SOM) | B34: =B35*B36*B37 -> 237600000 | C34: https://www.google.com/url?sa=t&rct=j&q=&esrc=s&source=web&cd=&cad=rja&uact=8&ved=2ahUKEwje86neo7-BAxVGH0QIHXRiCm8QFnoECA0QAw&url=https%3A%2F%2Fwww.usnews.com%2Fbest-colleges%2Funiversity-of-southern-california-1328%2Fstudent-life%23%3A~%3Atext%3DUniversity%2520of%2520Southern%2520California%2520has%2Cof%2520students%2520live%2520off%2520campus.&usg=AOvVaw3so-BIlLx_kML_MwHBDFRI&opi=89978449
A35: Percentage of usc students living near campus | B35: 0.36 | C35: https://www.google.com/url?sa=t&rct=j&q=&esrc=s&source=web&cd=&cad=rja&uact=8&ved=2ahUKEwje86neo7-BAxVGH0QIHXRiCm8QFnoECA0QAw&url=https%3A%2F%2Fwww.usnews.com%2Fbest-colleges%2Funiversity-of-southern-california-1328%2Fstudent-life%23%3A~%3Atext%3DUniversity%2520of%2520Southern%2520California%2520has%2Cof%2520students%2520live%2520off%2520campus.&usg=AOvVaw3so-BIlLx_kML_MwHBDFRI&opi=89978449
A36: Total number of USC student enrollment | B36: 44000
A37: Average per year cost of living per student | B37: 15000 | C37: https://housing.usc.edu/index.php/sample-cost/
A38: Students living near campus | B38: =B35*B36 -> 15840
A39: Typical customer growth rate for rating platform SaaS | B39: 0.15
A40: Typical deal charging USC (comparing with Lyft and similar programs) | B40: =1000*$B$35*$B$36 -> 15840000 | C40: USC Lyft program 1000 per student
A41: Universities addition | B41: 4
A42: Employee salaries | B42: 60000
A43: Per year per person analytics revenu | B43: 7500

Sheet Revenue Model 
A1: Revenue Model
A2: Time (yr) | B2: Users | C2: Advertising Revenue | D2: Revenue From Subcriptions | E2: Revenue from real estate alliance | F2: Revenue
A3: 1 | B3: =G18 -> 258000 | C3: =E$34*B3 -> 500000 | D3: =E$35*B3 -> 167700 | E3: =E$38*B3 -> 100000 | F3: =E$41*B3 -> 767700
A4: 2 | B4: =B3*(1+G$19) -> 283800 | C4: =E$34*B4 -> 550000 | D4: =E$35*B4 -> 184470 | E4: =E$38*B4 -> 110000 | F4: =E$41*B4 -> 844470
A5: 3 | B5: =B4*(1+G$19) -> 312180 | C5: =E$34*B5 -> 605000 | D5: =E$35*B5 -> 202917 | E5: =E$38*B5 -> 121000 | F5: =E$41*B5 -> 928917
A6: 4 | B6: =B5*(1+G$19) -> 343398 | C6: =E$34*B6 -> 665500 | D6: =E$35*B6 -> 223208.7 | E6: =E$38*B6 -> 133100 | F6: =E$41*B6 -> 1021808.7
A7: 5 | B7: =B6*(1+G$19) -> 377737.8 | C7: =E$34*B7 -> 732050 | D7: =E$35*B7 -> 245529.57 | E7: =E$38*B7 -> 146410 | F7: =E$41*B7 -> 1123989.6
A10: Market Sizing
A11: Total College Enrollment in the U.S. (2022) | G11: 20031000 | I11: https://educationdata.org/college-enrollment-statistics
A12: Occupancy Level of both on and off campus housing in the U.S. (2018) | G12: 0.94 | I12: https://www.casita.com/blog/student-housing-statistics-a-case-study
A13: Market Size | G13: =G12*G11 -> 18829140
A14: Percentage of students that have an active account on RateMyProffessor | G14: 0.33 | I14: https://www.insidehighered.com/advice/2019/10/10/tongue-cheek-announcement-new-portal-where-faculty-members-can-rate-their-students#:~:text=Roughly%20one%2Dthird%20of%20the,and%20minds%20of%20our%20students.
A15: Market Share | G15: =G13*G14 -> 6213616.2
A17: College Enrollment in California (2022) | G17: 2580000 | I17: https://educationdata.org/college-enrollment-statistics
A18: Expected User in year 1 | G18: =10%*G17 -> 258000
A19: Expected user growth per year | G19: 0.1
A33: Average Revenue Per User (APRU)
A34: APRU from expected advertising revenue in year 1 | E34: =500000/G18 -> 1.9379845
A35: APRU from expected revenue from subsriptions in year 1: | E35: =(E36*E37*G18)/G18 -> 0.65
A36: Average subcription fee per user | E36: =(70%*5)+(30%*10) -> 6.5
A37: Percentage of registered users opting for premium services | E37: 0.1
A38: APRU from expected revenue from real estate alliances in year 1: | E38: =(E39*E40)/G18 -> 0.3875969
A39: Annual partnership fee per alliance | E39: 5000
A40: Expected alliances in year 1 | E40: 20
A41: Average Revenue Per User ($/user) | E41: =(E34+E35+E38) -> 2.9755814
